vox2obj/__init__.py
vox2obj/vox2obj.py
vox2obj-0.1.0.dist-info/LICENSE
vox2obj-0.1.0.dist-info/METADATA
vox2obj-0.1.0.dist-info/WHEEL
vox2obj-0.1.0.dist-info/top_level.txt
vox2obj-0.1.0.dist-info/RECORD
