Metadata-Version: 2.1
Name: vox2obj
Version: 0.1.0
Summary: Converts voxel models to obj files.
Home-page: https://gitlab.com/Claytone/vox2obj
Author: Claytone
Author-email: clayton.wells.321@gmail.com
License: MIT
Project-URL: Bug Tracker, https://gitlab.com/Claytone/vox2obj/-/issues
Platform: UNKNOWN
Classifier: Programming Language :: Python :: 3
Classifier: License :: OSI Approved :: MIT License
Classifier: Operating System :: OS Independent
Requires-Python: >=3.6
License-File: LICENSE
